HISTORY.md
MANIFEST.in
README.md
VERSION
requirements.txt
setup.cfg
setup.py
ONEmSDK.egg-info/PKG-INFO
ONEmSDK.egg-info/SOURCES.txt
ONEmSDK.egg-info/dependency_links.txt
ONEmSDK.egg-info/requires.txt
ONEmSDK.egg-info/top_level.txt
onemsdk/__init__.py
onemsdk/config.py
onemsdk/exceptions.py
onemsdk/contrib/__init__.py
onemsdk/contrib/django.py
onemsdk/parser/__init__.py
onemsdk/parser/node.py
onemsdk/parser/tag.py
onemsdk/parser/util.py
onemsdk/schema/__init__.py
onemsdk/schema/v1.py