Metadata-Version: 2.1
Name: ONEmSDK
Version: 0.8.0
Summary: Python ONEm SDK
Home-page: https://github.com/romeo1m/onemsdk
Author: romeo1m
Author-email: romeo.tudureanu@onem.com
License: MIT
Download-URL: https://github.com/romeo1m/onemsdk
Project-URL: Source, https://github.com/romeo1m/onemsdk
Keywords: sdk onem python
Platform: UNKNOWN
Classifier: Development Status :: 3 - Alpha
Classifier: Intended Audience :: Developers
Classifier: Topic :: Software Development :: Build Tools
Classifier: License :: OSI Approved :: MIT License
Classifier: Programming Language :: Python :: 3.6
Classifier: Programming Language :: Python :: 3.7
Requires-Python: >=3.6, <4
